README.md
setup.cfg
setup.py
awsrotatekey/__init__.py
awsrotatekey/__main__.py
awsrotatekey/checkexpiry.py
awsrotatekey/expdict.py
awsrotatekey/includeexclude.py
awsrotatekey/operations.py
awsrotatekey/rotatekeys.py
awsrotatekey.egg-info/PKG-INFO
awsrotatekey.egg-info/SOURCES.txt
awsrotatekey.egg-info/dependency_links.txt
awsrotatekey.egg-info/entry_points.txt
awsrotatekey.egg-info/requires.txt
awsrotatekey.egg-info/top_level.txt