Metadata-Version: 2.1
Name: awsrotatekey
Version: 5.0
Summary: Rotate AWS keys for any user.
Home-page: UNKNOWN
Author: Kanishk Saxena
Author-email: kanishk.saxena@cred.club
License: MIT
Keywords: AWS,Rotate,Keys
Platform: UNKNOWN
Classifier: Development Status :: 4 - Beta
Classifier: Intended Audience :: Developers
Classifier: License :: OSI Approved :: MIT License
Classifier: Programming Language :: Python :: 2
Classifier: Programming Language :: Python :: 2.7
